{
    "sourceFile": "src/styles/blocks/_links.scss",
    "activeCommit": 0,
    "commits": [
        {
            "activePatchIndex": 29,
            "patches": [
                {
                    "date": 1707935844812,
                    "content": "Index: \n===================================================================\n--- \n+++ \n"
                },
                {
                    "date": 1707935861222,
                    "content": "Index: \n===================================================================\n--- \n+++ \n@@ -1,3 +1,3 @@\n .links {\n-  \n+  &__\n }\n"
                },
                {
                    "date": 1707935876351,
                    "content": "Index: \n===================================================================\n--- \n+++ \n@@ -1,3 +1,3 @@\n .links {\n-  &__\n+  &__list {}\n }\n"
                },
                {
                    "date": 1707935884709,
                    "content": "Index: \n===================================================================\n--- \n+++ \n@@ -0,0 +1,8 @@\n+.links {\n+  &__list {\n+\n+  }\n+  &__item {\n+\n+  }\n+}\n"
                },
                {
                    "date": 1707935891749,
                    "content": "Index: \n===================================================================\n--- \n+++ \n@@ -4,8 +4,8 @@\n   }\n   &__item {\n \n   }\n+  &__link {\n+    \n+  }\n }\n-.links {\n-  &__list {}\n-}\n"
                },
                {
                    "date": 1707935897296,
                    "content": "Index: \n===================================================================\n--- \n+++ \n@@ -1,11 +1,13 @@\n .links {\n+\n   &__list {\n \n   }\n+  \n   &__item {\n \n   }\n   &__link {\n-    \n+\n   }\n }\n"
                },
                {
                    "date": 1707936167645,
                    "content": "Index: \n===================================================================\n--- \n+++ \n@@ -0,0 +1,14 @@\n+.links {\n+\n+  &__list {\n+color: adjust-color($color: #000000, $red: 1, $green: 2, $blue: 3, $hue: 0, $saturation: 0%, $lightness: 0%, $alpha: 1.0);\n+  }\n+\n+  &__item {\n+\n+  }\n+\n+  &__link {\n+\n+  }\n+}\n"
                },
                {
                    "date": 1707936176039,
                    "content": "Index: \n===================================================================\n--- \n+++ \n@@ -0,0 +1,14 @@\n+.links {\n+\n+  &__list {\n+color: adjust-color($color: #000000, $red: 1, $green: 2, $blue: 3, $hue: 0, $saturation: 0%, $lightness: 0%, $alpha: 1.0);\n+  }\n+\n+  &__item {\n+color: adjust-color($color: #000000, $red: 1, $green: 2, $blue: 3, $hue: 0, $saturation: 0%, $lightness: 0%, $alpha: 1.0);\n+  }\n+\n+  &__link {\n+\n+  }\n+}\n"
                },
                {
                    "date": 1707936202294,
                    "content": "Index: \n===================================================================\n--- \n+++ \n@@ -1,41 +1,14 @@\n .links {\n \n   &__list {\n-color: adjust-color($color: #000000, $red: 1, $green: 2, $blue: 3, $hue: 0, $saturation: 0%, $lightness: 0%, $alpha: 1.0);\n+color: ;\n   }\n \n   &__item {\n-color: adjust-color($color: #000000, $red: 1, $green: 2, $blue: 3, $hue: 0, $saturation: 0%, $lightness: 0%, $alpha: 1.0);\n-  }\n \n-  &__link {\n-\n   }\n-}\n-.links {\n \n-  &__list {\n-color: adjust-color($color: #000000, $red: 1, $green: 2, $blue: 3, $hue: 0, $saturation: 0%, $lightness: 0%, $alpha: 1.0);\n-  }\n-\n-  &__item {\n-\n-  }\n-\n   &__link {\n \n   }\n }\n-.links {\n-\n-  &__list {\n-\n-  }\n-  \n-  &__item {\n-\n-  }\n-  &__link {\n-\n-  }\n-}\n"
                },
                {
                    "date": 1707936210442,
                    "content": "Index: \n===================================================================\n--- \n+++ \n@@ -1,12 +1,12 @@\n .links {\n \n   &__list {\n-color: ;\n+color: beige;\n   }\n \n   &__item {\n-\n+color: beige;\n   }\n \n   &__link {\n \n"
                },
                {
                    "date": 1707936447619,
                    "content": "Index: \n===================================================================\n--- \n+++ \n@@ -0,0 +1,19 @@\n+.links {\n+\n+  &__list {\n+color: beige;\n+  }\n+\n+  &__item {\n+color: beige;\n+  }\n+\n+  &__link {font-family: Cinzel;\n+font-size: 22px;\n+font-weight: 700;\n+line-height: 22px;\n+letter-spacing: 2px;\n+text-align: left;\n+\n+  }\n+}\n"
                },
                {
                    "date": 1707936454980,
                    "content": "Index: \n===================================================================\n--- \n+++ \n@@ -0,0 +1,20 @@\n+.links {\n+\n+  &__list {\n+color: beige;\n+  }\n+\n+  &__item {\n+color: beige;\n+  }\n+\n+  &__link {\n+    font-family: Cinzel;\n+    font-size: 22px;\n+    font-weight: 700;\n+    line-height: 22px;\n+    letter-spacing: 2px;\n+    text-align: left;\n+\n+  }\n+}\n"
                },
                {
                    "date": 1707936638445,
                    "content": "Index: \n===================================================================\n--- \n+++ \n@@ -8,46 +8,12 @@\n color: beige;\n   }\n \n   &__link {\n-    font-family: Cinzel;\n+    font-family: Cinzel, sans-serif;\n     font-size: 22px;\n     font-weight: 700;\n     line-height: 22px;\n     letter-spacing: 2px;\n     text-align: left;\n-\n   }\n }\n-.links {\n-\n-  &__list {\n-color: beige;\n-  }\n-\n-  &__item {\n-color: beige;\n-  }\n-\n-  &__link {font-family: Cinzel;\n-font-size: 22px;\n-font-weight: 700;\n-line-height: 22px;\n-letter-spacing: 2px;\n-text-align: left;\n-\n-  }\n-}\n-.links {\n-\n-  &__list {\n-color: beige;\n-  }\n-\n-  &__item {\n-color: beige;\n-  }\n-\n-  &__link {\n-\n-  }\n-}\n"
                },
                {
                    "date": 1707936672008,
                    "content": "Index: \n===================================================================\n--- \n+++ \n@@ -0,0 +1,20 @@\n+.links {\n+\n+  &__list {\n+color: beige;\n+  }\n+\n+  &__item {\n+color: beige;\n+  }\n+\n+  &__link {\n+    font-family: Cinzel, sans-serif;\n+    font-size: 22px;\n+    font-weight: 700;\n+    line-height: 22px;\n+    letter-spacing: 2px;\n+    text-align: left;\n+    td\n+  }\n+}\n"
                },
                {
                    "date": 1707936687075,
                    "content": "Index: \n===================================================================\n--- \n+++ \n@@ -0,0 +1,21 @@\n+.links {\n+\n+  &__list {\n+color: beige;\n+  }\n+\n+  &__item {\n+color: beige;\n+  }\n+\n+  &__link {\n+    font-family: Cinzel, sans-serif;\n+    font-size: 22px;\n+    font-weight: 700;\n+    line-height: 22px;\n+    letter-spacing: 2px;\n+    text-align: left;\n+    text-decoration: none;\n+    color: ;\n+  }\n+}\n"
                },
                {
                    "date": 1707936719161,
                    "content": "Index: \n===================================================================\n--- \n+++ \n@@ -15,46 +15,7 @@\n     line-height: 22px;\n     letter-spacing: 2px;\n     text-align: left;\n     text-decoration: none;\n-    color: ;\n+    color: #fff;\n   }\n }\n-.links {\n-\n-  &__list {\n-color: beige;\n-  }\n-\n-  &__item {\n-color: beige;\n-  }\n-\n-  &__link {\n-    font-family: Cinzel, sans-serif;\n-    font-size: 22px;\n-    font-weight: 700;\n-    line-height: 22px;\n-    letter-spacing: 2px;\n-    text-align: left;\n-    td\n-  }\n-}\n-.links {\n-\n-  &__list {\n-color: beige;\n-  }\n-\n-  &__item {\n-color: beige;\n-  }\n-\n-  &__link {\n-    font-family: Cinzel, sans-serif;\n-    font-size: 22px;\n-    font-weight: 700;\n-    line-height: 22px;\n-    letter-spacing: 2px;\n-    text-align: left;\n-  }\n-}\n"
                },
                {
                    "date": 1707936729865,
                    "content": "Index: \n===================================================================\n--- \n+++ \n@@ -16,6 +16,7 @@\n     letter-spacing: 2px;\n     text-align: left;\n     text-decoration: none;\n     color: #fff;\n+    border\n   }\n }\n"
                },
                {
                    "date": 1707936747595,
                    "content": "Index: \n===================================================================\n--- \n+++ \n@@ -0,0 +1,21 @@\n+.links {\n+\n+  &__list {\n+color: beige;\n+  }\n+\n+  &__item {\n+color: beige;\n+  }\n+\n+  &__link {\n+    font-family: Cinzel, sans-serif;\n+    font-size: 22px;\n+    font-weight: 700;\n+    line-height: 22px;\n+    letter-spacing: 2px;\n+    text-align: left;\n+    text-decoration: none;\n+    color: #fff;\n+  }\n+}\n"
                },
                {
                    "date": 1707936882258,
                    "content": "Index: \n===================================================================\n--- \n+++ \n@@ -16,28 +16,7 @@\n     letter-spacing: 2px;\n     text-align: left;\n     text-decoration: none;\n     color: #fff;\n+    \n   }\n }\n-.links {\n-\n-  &__list {\n-color: beige;\n-  }\n-\n-  &__item {\n-color: beige;\n-  }\n-\n-  &__link {\n-    font-family: Cinzel, sans-serif;\n-    font-size: 22px;\n-    font-weight: 700;\n-    line-height: 22px;\n-    letter-spacing: 2px;\n-    text-align: left;\n-    text-decoration: none;\n-    color: #fff;\n-    border\n-  }\n-}\n"
                },
                {
                    "date": 1707936888707,
                    "content": "Index: \n===================================================================\n--- \n+++ \n@@ -16,7 +16,7 @@\n     letter-spacing: 2px;\n     text-align: left;\n     text-decoration: none;\n     color: #fff;\n-    \n+    padding\n   }\n }\n"
                },
                {
                    "date": 1707936896805,
                    "content": "Index: \n===================================================================\n--- \n+++ \n@@ -16,7 +16,7 @@\n     letter-spacing: 2px;\n     text-align: left;\n     text-decoration: none;\n     color: #fff;\n-    padding\n+    padding-bottom: 32px;\n   }\n }\n"
                },
                {
                    "date": 1707936927062,
                    "content": "Index: \n===================================================================\n--- \n+++ \n@@ -16,7 +16,7 @@\n     letter-spacing: 2px;\n     text-align: left;\n     text-decoration: none;\n     color: #fff;\n-    padding-bottom: 32px;\n+    padding-bottom: 40px;\n   }\n }\n"
                },
                {
                    "date": 1707936958626,
                    "content": "Index: \n===================================================================\n--- \n+++ \n@@ -16,7 +16,6 @@\n     letter-spacing: 2px;\n     text-align: left;\n     text-decoration: none;\n     color: #fff;\n-    padding-bottom: 40px;\n   }\n }\n"
                },
                {
                    "date": 1707936983408,
                    "content": "Index: \n===================================================================\n--- \n+++ \n@@ -16,6 +16,7 @@\n     letter-spacing: 2px;\n     text-align: left;\n     text-decoration: none;\n     color: #fff;\n+    padding-bottom: 40px;\n   }\n }\n"
                },
                {
                    "date": 1707937015821,
                    "content": "Index: \n===================================================================\n--- \n+++ \n@@ -8,8 +8,9 @@\n color: beige;\n   }\n \n   &__link {\n+    \n     font-family: Cinzel, sans-serif;\n     font-size: 22px;\n     font-weight: 700;\n     line-height: 22px;\n"
                },
                {
                    "date": 1707937021850,
                    "content": "Index: \n===================================================================\n--- \n+++ \n@@ -0,0 +1,23 @@\n+.links {\n+\n+  &__list {\n+color: beige;\n+  }\n+\n+  &__item {\n+color: beige;\n+  }\n+\n+  &__link {\n+    display: inline-block;\n+    font-family: Cinzel, sans-serif;\n+    font-size: 22px;\n+    font-weight: 700;\n+    line-height: 22px;\n+    letter-spacing: 2px;\n+    text-align: left;\n+    text-decoration: none;\n+    color: #fff;\n+    padding-bottom: 40px;\n+  }\n+}\n"
                },
                {
                    "date": 1707937045286,
                    "content": "Index: \n===================================================================\n--- \n+++ \n@@ -0,0 +1,23 @@\n+.links {\n+\n+  &__list {\n+color: beige;\n+  }\n+\n+  &__item {\n+color: beige;\n+  }\n+\n+  &__link {\n+    display: inline-block;\n+    font-family: Cinzel, sans-serif;\n+    font-size: 22px;\n+    font-weight: 700;\n+    line-height: 22px;\n+    letter-spacing: 2px;\n+    text-align: left;\n+    text-decoration: none;\n+    color: #fff;\n+    padding-bottom: 32px;\n+  }\n+}\n"
                },
                {
                    "date": 1707937278600,
                    "content": "Index: \n===================================================================\n--- \n+++ \n@@ -1,5 +1,6 @@\n .links {\n+  padding\n \n   &__list {\n color: beige;\n   }\n@@ -20,50 +21,4 @@\n     color: #fff;\n     padding-bottom: 32px;\n   }\n }\n-.links {\n-\n-  &__list {\n-color: beige;\n-  }\n-\n-  &__item {\n-color: beige;\n-  }\n-\n-  &__link {\n-    display: inline-block;\n-    font-family: Cinzel, sans-serif;\n-    font-size: 22px;\n-    font-weight: 700;\n-    line-height: 22px;\n-    letter-spacing: 2px;\n-    text-align: left;\n-    text-decoration: none;\n-    color: #fff;\n-    padding-bottom: 40px;\n-  }\n-}\n-.links {\n-\n-  &__list {\n-color: beige;\n-  }\n-\n-  &__item {\n-color: beige;\n-  }\n-\n-  &__link {\n-    \n-    font-family: Cinzel, sans-serif;\n-    font-size: 22px;\n-    font-weight: 700;\n-    line-height: 22px;\n-    letter-spacing: 2px;\n-    text-align: left;\n-    text-decoration: none;\n-    color: #fff;\n-    padding-bottom: 40px;\n-  }\n-}\n"
                },
                {
                    "date": 1707937299861,
                    "content": "Index: \n===================================================================\n--- \n+++ \n@@ -0,0 +1,23 @@\n+.links {\n+\n+  &__list {\n+color: beige;\n+  }\n+\n+  &__item {\n+color: beige;\n+  }\n+\n+  &__link {\n+    display: inline-block;\n+    font-family: Cinzel, sans-serif;\n+    font-size: 22px;\n+    font-weight: 700;\n+    line-height: 22px;\n+    letter-spacing: 2px;\n+    text-align: left;\n+    text-decoration: none;\n+    color: #fff;\n+    padding-bottom: 32px;\n+  }\n+}\n"
                },
                {
                    "date": 1707937330968,
                    "content": "Index: \n===================================================================\n--- \n+++ \n@@ -20,28 +20,4 @@\n     color: #fff;\n     padding-bottom: 32px;\n   }\n }\n-.links {\n-  padding\n-\n-  &__list {\n-color: beige;\n-  }\n-\n-  &__item {\n-color: beige;\n-  }\n-\n-  &__link {\n-    display: inline-block;\n-    font-family: Cinzel, sans-serif;\n-    font-size: 22px;\n-    font-weight: 700;\n-    line-height: 22px;\n-    letter-spacing: 2px;\n-    text-align: left;\n-    text-decoration: none;\n-    color: #fff;\n-    padding-bottom: 32px;\n-  }\n-}\n"
                }
            ],
            "date": 1707935844812,
            "name": "Commit-0",
            "content": ".links {\n  \n}\n"
        }
    ]
}