{
    "sourceFile": "src/scripts/main.js",
    "activeCommit": 0,
    "commits": [
        {
            "activePatchIndex": 11,
            "patches": [
                {
                    "date": 1708180636010,
                    "content": "Index: \n===================================================================\n--- \n+++ \n"
                },
                {
                    "date": 1708180764370,
                    "content": "Index: \n===================================================================\n--- \n+++ \n@@ -6,4 +6,6 @@\n   } else {\n     document.body.classList.remove('page__body--with-menu');\n   }\n });\n+\n+document.qs\n"
                },
                {
                    "date": 1708180770381,
                    "content": "Index: \n===================================================================\n--- \n+++ \n@@ -7,5 +7,5 @@\n     document.body.classList.remove('page__body--with-menu');\n   }\n });\n \n-document.qs\n+document.querySelectorAll()\n"
                },
                {
                    "date": 1708180812087,
                    "content": "Index: \n===================================================================\n--- \n+++ \n@@ -0,0 +1,11 @@\n+'use strict';\n+\n+window.addEventListener('hashchange', () => {\n+  if (window.location.hash === '#menu') {\n+    document.body.classList.add('page__body--with-menu');\n+  } else {\n+    document.body.classList.remove('page__body--with-menu');\n+  }\n+});\n+\n+document.querySelectorAll(\"\")\n"
                },
                {
                    "date": 1708180838567,
                    "content": "Index: \n===================================================================\n--- \n+++ \n@@ -7,16 +7,5 @@\n     document.body.classList.remove('page__body--with-menu');\n   }\n });\n \n-document.querySelectorAll(\"\")\n-'use strict';\n-\n-window.addEventListener('hashchange', () => {\n-  if (window.location.hash === '#menu') {\n-    document.body.classList.add('page__body--with-menu');\n-  } else {\n-    document.body.classList.remove('page__body--with-menu');\n-  }\n-});\n-\n-document.querySelectorAll()\n+const preventDefault = document.querySelectorAll(\".form__prevent\")\n"
                },
                {
                    "date": 1708180845407,
                    "content": "Index: \n===================================================================\n--- \n+++ \n@@ -7,5 +7,7 @@\n     document.body.classList.remove('page__body--with-menu');\n   }\n });\n \n-const preventDefault = document.querySelectorAll(\".form__prevent\")\n+const preventDefault = document.querySelectorAll(\".form__prevent\");\n+\n+preventDefault\n"
                },
                {
                    "date": 1708180862058,
                    "content": "Index: \n===================================================================\n--- \n+++ \n@@ -9,5 +9,5 @@\n });\n \n const preventDefault = document.querySelectorAll(\".form__prevent\");\n \n-preventDefault\n+preventDefault.add\n"
                },
                {
                    "date": 1708180874342,
                    "content": "Index: \n===================================================================\n--- \n+++ \n@@ -0,0 +1,13 @@\n+'use strict';\n+\n+window.addEventListener('hashchange', () => {\n+  if (window.location.hash === '#menu') {\n+    document.body.classList.add('page__body--with-menu');\n+  } else {\n+    document.body.classList.remove('page__body--with-menu');\n+  }\n+});\n+\n+const preventDefault = document.querySelectorAll(\".form__prevent\");\n+\n+preventDefault.addEventListener(\"click\", check)\n"
                },
                {
                    "date": 1708180888843,
                    "content": "Index: \n===================================================================\n--- \n+++ \n@@ -9,18 +9,7 @@\n });\n \n const preventDefault = document.querySelectorAll(\".form__prevent\");\n \n-preventDefault.addEventListener(\"click\", check)\n-'use strict';\n+preventDefault.addEventListener(\"click\", check);\n \n-window.addEventListener('hashchange', () => {\n-  if (window.location.hash === '#menu') {\n-    document.body.classList.add('page__body--with-menu');\n-  } else {\n-    document.body.classList.remove('page__body--with-menu');\n-  }\n-});\n-\n-const preventDefault = document.querySelectorAll(\".form__prevent\");\n-\n-preventDefault.add\n+function check {}\n"
                },
                {
                    "date": 1708180894526,
                    "content": "Index: \n===================================================================\n--- \n+++ \n@@ -0,0 +1,15 @@\n+'use strict';\n+\n+window.addEventListener('hashchange', () => {\n+  if (window.location.hash === '#menu') {\n+    document.body.classList.add('page__body--with-menu');\n+  } else {\n+    document.body.classList.remove('page__body--with-menu');\n+  }\n+});\n+\n+const preventDefault = document.querySelectorAll(\".form__prevent\");\n+\n+preventDefault.addEventListener(\"click\", check);\n+\n+function check(e)\n"
                },
                {
                    "date": 1708180907844,
                    "content": "Index: \n===================================================================\n--- \n+++ \n@@ -11,20 +11,7 @@\n const preventDefault = document.querySelectorAll(\".form__prevent\");\n \n preventDefault.addEventListener(\"click\", check);\n \n-function check(e)\n-'use strict';\n-\n-window.addEventListener('hashchange', () => {\n-  if (window.location.hash === '#menu') {\n-    document.body.classList.add('page__body--with-menu');\n-  } else {\n-    document.body.classList.remove('page__body--with-menu');\n-  }\n-});\n-\n-const preventDefault = document.querySelectorAll(\".form__prevent\");\n-\n-preventDefault.addEventListener(\"click\", check);\n-\n-function check {}\n+function check(e) {\n+  e.preventDefault();\n+}\n"
                },
                {
                    "date": 1708180993750,
                    "content": "Index: \n===================================================================\n--- \n+++ \n@@ -9,9 +9,9 @@\n });\n \n const preventDefault = document.querySelectorAll(\".form__prevent\");\n \n-preventDefault.addEventListener(\"click\", check);\n+preventDefault.addEventListener(\"click\", check, false);\n \n function check(e) {\n   e.preventDefault();\n }\n"
                }
            ],
            "date": 1708180636010,
            "name": "Commit-0",
            "content": "'use strict';\n\nwindow.addEventListener('hashchange', () => {\n  if (window.location.hash === '#menu') {\n    document.body.classList.add('page__body--with-menu');\n  } else {\n    document.body.classList.remove('page__body--with-menu');\n  }\n});\n"
        }
    ]
}